baopingjimokuai.py
baotest/__init__.py
baotest/baoneimokuai.py
xiangmutest-1.0.0.dist-info/LICENSE.txt
xiangmutest-1.0.0.dist-info/METADATA
xiangmutest-1.0.0.dist-info/WHEEL
xiangmutest-1.0.0.dist-info/top_level.txt
xiangmutest-1.0.0.dist-info/RECORD
